kk592/p1.py
kk592/setup.py
kk592-0.1.dist-info/METADATA
kk592-0.1.dist-info/WHEEL
kk592-0.1.dist-info/top_level.txt
kk592-0.1.dist-info/RECORD
