Metadata-Version: 2.1
Name: kk592
Version: 0.1
Summary: good mrng
Home-page: http://github.com/storborg/funniest
Author: Kamal Kumar
Author-email: kamalsir@ymail.com
License: MIT
Platform: UNKNOWN
